{"config":{"output_file":null,"full_docs":false,"pub_only":false,"reachable_only":false,"distro_crate":false,"signatures":false,"borrow_data":false},"version":"0.19.0","compilation":{"directory":"/home/dnrops/code/github/learn_notes/rust","program":"/home/dnrops/.rustup/toolchains/stable-x86_64-unknown-linux-gnu/bin/rls","arguments":[],"output":"/home/dnrops/code/github/learn_notes/rust/target/rls/debug/deps/librust-aef18fce8a246641.rmeta"},"prelude":{"crate_id":{"name":"rust","disambiguator":[17929546904039511662,209157768172781926]},"crate_root":"src","external_crates":[{"file_name":"/home/dnrops/code/github/learn_notes/rust/src/main.rs","num":1,"id":{"name":"std","disambiguator":[4418738106075590160,6298063093324017560]}},{"file_name":"/home/dnrops/code/github/learn_notes/rust/src/main.rs","num":2,"id":{"name":"core","disambiguator":[9113878364975505769,4626460723841361367]}},{"file_name":"/home/dnrops/code/github/learn_notes/rust/src/main.rs","num":3,"id":{"name":"compiler_builtins","disambiguator":[10636203250160794641,6979396832464280682]}},{"file_name":"/home/dnrops/code/github/learn_notes/rust/src/main.rs","num":4,"id":{"name":"rustc_std_workspace_core","disambiguator":[7259142600435629501,12221323364939802703]}},{"file_name":"/home/dnrops/code/github/learn_notes/rust/src/main.rs","num":5,"id":{"name":"alloc","disambiguator":[245280942947536957,12219005383890086938]}},{"file_name":"/home/dnrops/code/github/learn_notes/rust/src/main.rs","num":6,"id":{"name":"libc","disambiguator":[6161946279237914842,16521306710208745576]}},{"file_name":"/home/dnrops/code/github/learn_notes/rust/src/main.rs","num":7,"id":{"name":"unwind","disambiguator":[6542909105960794691,9677219093962929367]}},{"file_name":"/home/dnrops/code/github/learn_notes/rust/src/main.rs","num":8,"id":{"name":"cfg_if","disambiguator":[5468829561226316808,7834745881253856659]}},{"file_name":"/home/dnrops/code/github/learn_notes/rust/src/main.rs","num":9,"id":{"name":"hashbrown","disambiguator":[17700629721805382410,8884445337419759755]}},{"file_name":"/home/dnrops/code/github/learn_notes/rust/src/main.rs","num":10,"id":{"name":"rustc_std_workspace_alloc","disambiguator":[5673318663856259921,7992701887106127366]}},{"file_name":"/home/dnrops/code/github/learn_notes/rust/src/main.rs","num":11,"id":{"name":"backtrace","disambiguator":[14096840682646779984,4894716104918169263]}},{"file_name":"/home/dnrops/code/github/learn_notes/rust/src/main.rs","num":12,"id":{"name":"rustc_demangle","disambiguator":[17167590092810160364,15681868143498786567]}},{"file_name":"/home/dnrops/code/github/learn_notes/rust/src/main.rs","num":13,"id":{"name":"backtrace_sys","disambiguator":[9809686796458150241,12960706147778414440]}},{"file_name":"/home/dnrops/code/github/learn_notes/rust/src/main.rs","num":14,"id":{"name":"panic_unwind","disambiguator":[14218938340851961837,11099897245983054425]}},{"file_name":"/home/dnrops/code/github/learn_notes/rust/src/main.rs","num":15,"id":{"name":"test","disambiguator":[6128194586364497561,2254427030762643493]}},{"file_name":"/home/dnrops/code/github/learn_notes/rust/src/main.rs","num":16,"id":{"name":"getopts","disambiguator":[14569919691843820440,11539076949874791119]}},{"file_name":"/home/dnrops/code/github/learn_notes/rust/src/main.rs","num":17,"id":{"name":"unicode_width","disambiguator":[10259995004392141789,10619846379592895111]}},{"file_name":"/home/dnrops/code/github/learn_notes/rust/src/main.rs","num":18,"id":{"name":"term","disambiguator":[16002564112529110979,7561850491337890633]}}],"span":{"file_name":"src/main.rs","byte_start":194,"byte_end":472,"line_start":12,"line_end":36,"column_start":1,"column_end":2}},"imports":[],"defs":[{"kind":"Mod","id":{"krate":0,"index":0},"span":{"file_name":"src/main.rs","byte_start":194,"byte_end":472,"line_start":12,"line_end":36,"column_start":1,"column_end":2},"name":"","qualname":"::","value":"src/main.rs","parent":null,"children":[{"krate":0,"index":10},{"krate":0,"index":11},{"krate":0,"index":12},{"krate":0,"index":19},{"krate":0,"index":20}],"decl_id":null,"docs":"","sig":null,"attributes":[]},{"kind":"Mod","id":{"krate":0,"index":12},"span":{"file_name":"src/structs.rs","byte_start":0,"byte_end":0,"line_start":1,"line_end":1,"column_start":1,"column_end":1},"name":"structs","qualname":"::structs","value":"src/structs.rs","parent":null,"children":[{"krate":0,"index":13},{"krate":0,"index":18}],"decl_id":null,"docs":"","sig":null,"attributes":[]},{"kind":"Struct","id":{"krate":0,"index":13},"span":{"file_name":"src/structs.rs","byte_start":579,"byte_end":584,"line_start":9,"line_end":9,"column_start":8,"column_end":13},"name":"Color","qualname":"::structs::Color","value":"","parent":null,"children":[],"decl_id":null,"docs":"","sig":null,"attributes":[]},{"kind":"Function","id":{"krate":0,"index":18},"span":{"file_name":"src/structs.rs","byte_start":603,"byte_end":606,"line_start":10,"line_end":10,"column_start":8,"column_end":11},"name":"run","qualname":"::structs::run","value":"fn () -> ()","parent":null,"children":[],"decl_id":null,"docs":"","sig":null,"attributes":[]},{"kind":"Local","id":{"krate":0,"index":4294967270},"span":{"file_name":"src/structs.rs","byte_start":778,"byte_end":779,"line_start":18,"line_end":18,"column_start":9,"column_end":10},"name":"c","qualname":"c$25","value":"structs::Color","parent":null,"children":[],"decl_id":null,"docs":"","sig":null,"attributes":[]},{"kind":"Function","id":{"krate":0,"index":19},"span":{"file_name":"src/main.rs","byte_start":215,"byte_end":219,"line_start":18,"line_end":18,"column_start":4,"column_end":8},"name":"main","qualname":"::main","value":"fn () -> ()","parent":null,"children":[],"decl_id":null,"docs":"","sig":null,"attributes":[{"value":"allow(dead_code)","span":{"file_name":"src/main.rs","byte_start":0,"byte_end":0,"line_start":1,"line_end":1,"column_start":1,"column_end":1}}]}],"impls":[],"refs":[{"kind":"Mod","span":{"file_name":"src/main.rs","byte_start":198,"byte_end":205,"line_start":12,"line_end":12,"column_start":5,"column_end":12},"ref_id":{"krate":0,"index":12}},{"kind":"Type","span":{"file_name":"src/structs.rs","byte_start":780,"byte_end":785,"line_start":18,"line_end":18,"column_start":11,"column_end":16},"ref_id":{"krate":0,"index":13}},{"kind":"Variable","span":{"file_name":"src/structs.rs","byte_start":822,"byte_end":823,"line_start":19,"line_end":19,"column_start":27,"column_end":28},"ref_id":{"krate":0,"index":4294967270}},{"kind":"Variable","span":{"file_name":"src/structs.rs","byte_start":824,"byte_end":825,"line_start":19,"line_end":19,"column_start":29,"column_end":30},"ref_id":{"krate":0,"index":15}},{"kind":"Variable","span":{"file_name":"src/structs.rs","byte_start":826,"byte_end":827,"line_start":19,"line_end":19,"column_start":31,"column_end":32},"ref_id":{"krate":0,"index":4294967270}},{"kind":"Variable","span":{"file_name":"src/structs.rs","byte_start":828,"byte_end":829,"line_start":19,"line_end":19,"column_start":33,"column_end":34},"ref_id":{"krate":0,"index":16}},{"kind":"Variable","span":{"file_name":"src/structs.rs","byte_start":830,"byte_end":831,"line_start":19,"line_end":19,"column_start":35,"column_end":36},"ref_id":{"krate":0,"index":4294967270}},{"kind":"Variable","span":{"file_name":"src/structs.rs","byte_start":832,"byte_end":833,"line_start":19,"line_end":19,"column_start":37,"column_end":38},"ref_id":{"krate":0,"index":17}},{"kind":"Function","span":{"file_name":"src/main.rs","byte_start":459,"byte_end":462,"line_start":30,"line_end":30,"column_start":15,"column_end":18},"ref_id":{"krate":0,"index":18}},{"kind":"Mod","span":{"file_name":"src/main.rs","byte_start":450,"byte_end":457,"line_start":30,"line_end":30,"column_start":6,"column_end":13},"ref_id":{"krate":0,"index":12}}],"macro_refs":[],"relations":[]}